README.md
setup.py
co6co.clash.egg-info/PKG-INFO
co6co.clash.egg-info/SOURCES.txt
co6co.clash.egg-info/dependency_links.txt
co6co.clash.egg-info/top_level.txt
co6co.clash.egg-info/zip-safe
co6co_clash/__init__.py
co6co_clash/node.py
co6co_clash/nodeLink.py
co6co_clash/nodes.py