Metadata-Version: 2.1
Name: co6co.clash
Version: 0.0.1
Summary: Clash 基础模块
Home-page: http://git.hub.com/Clash
Author: Clash
Author-email: Clash@qq.com
Classifier: Programming Language :: Python :: 3
Classifier: Programming Language :: Python :: 3.6
